pipub/__init__.py
pipub/cli.py
pipub-0.1.1.dist-info/LICENSE
pipub-0.1.1.dist-info/METADATA
pipub-0.1.1.dist-info/WHEEL
pipub-0.1.1.dist-info/entry_points.txt
pipub-0.1.1.dist-info/top_level.txt
pipub-0.1.1.dist-info/RECORD
